nycdb/__init__.py
nycdb/address.py
nycdb/annual_sales.py
nycdb/bbl.py
nycdb/cli.py
nycdb/database.py
nycdb/dataset.py
nycdb/dataset_transformations.py
nycdb/datasets.py
nycdb/dof_421a.py
nycdb/file.py
nycdb/shapefile.py
nycdb/sql.py
nycdb/transform.py
nycdb/typecast.py
nycdb/utility.py
nycdb/datasets/acris.yml
nycdb/datasets/boundaries.yml
nycdb/datasets/boundaries_25a.yml
nycdb/datasets/boundaries_water_included.yml
nycdb/datasets/boundaries_water_included_25a.yml
nycdb/datasets/dcp_housingdb.yml
nycdb/datasets/dhs_daily_shelter_count.yml
nycdb/datasets/dob_certificate_occupancy.yml
nycdb/datasets/dob_complaints.yml
nycdb/datasets/dob_safety_violations.yml
nycdb/datasets/dob_vacate_orders.yml
nycdb/datasets/dob_violations.yml
nycdb/datasets/dobjobs.yml
nycdb/datasets/dof_421a.yml
nycdb/datasets/dof_annual_sales.yml
nycdb/datasets/dof_exemptions.yml
nycdb/datasets/dof_property_valuation_and_assessments.yml
nycdb/datasets/dof_sales.yml
nycdb/datasets/dof_tax_lien_sale_list.yml
nycdb/datasets/dohmh_rodent_inspections.yml
nycdb/datasets/dos_active_corporations.yml
nycdb/datasets/ecb_violations.yml
nycdb/datasets/fc_shd.yml
nycdb/datasets/hpd_aep.yml
nycdb/datasets/hpd_affordable_production.yml
nycdb/datasets/hpd_charges.yml
nycdb/datasets/hpd_complaints.yml
nycdb/datasets/hpd_conh.yml
nycdb/datasets/hpd_litigations.yml
nycdb/datasets/hpd_ll44.yml
nycdb/datasets/hpd_registrations.yml
nycdb/datasets/hpd_underlying_conditions.yml
nycdb/datasets/hpd_vacateorders.yml
nycdb/datasets/hpd_violations.yml
nycdb/datasets/j51_exemptions.yml
nycdb/datasets/marshal_evictions.yml
nycdb/datasets/mci_applications.yml
nycdb/datasets/nycha_bbls.yml
nycdb/datasets/oath_hearings.yml
nycdb/datasets/oca.yml
nycdb/datasets/pad.yml
nycdb/datasets/pluto_10v1.yml
nycdb/datasets/pluto_15v1.yml
nycdb/datasets/pluto_16v2.yml
nycdb/datasets/pluto_17v1.yml
nycdb/datasets/pluto_18v1.yml
nycdb/datasets/pluto_18v2.yml
nycdb/datasets/pluto_19v1.yml
nycdb/datasets/pluto_19v2.yml
nycdb-0.4.1.dist-info/METADATA
nycdb-0.4.1.dist-info/WHEEL
nycdb-0.4.1.dist-info/entry_points.txt
nycdb-0.4.1.dist-info/top_level.txt
nycdb-0.4.1.dist-info/RECORD
