Metadata-Version: 2.4
Name: nycdb
Version: 0.4.1
Summary: Database of NYC housing data
Author-email: nycdb <nycdb@riseup.net>
License: AGPL-3.0-or-later
Project-URL: homepage, https://github.com/nycdb/nycdb
Project-URL: repository, https://github.com/nycdb/nycdb
Keywords: nyc,housing,data,postgresql
Classifier: License :: OSI Approved :: GNU Affero General Public License v3 or later (AGPLv3+)
Classifier: Programming Language :: Python :: 3 :: Only
Requires-Python: >=3.8
Requires-Dist: PyYAML>=5.1
Requires-Dist: requests>=2.18
Requires-Dist: psycopg>=3.1
Requires-Dist: tqdm>=4.28.1
Requires-Dist: openpyxl>=3.0.9
Requires-Dist: xlrd>=2.0.1
Provides-Extra: test
Requires-Dist: pytest>=6; extra == "test"
